spyctl/__init__.py
spyctl/cache_dict.py
spyctl/cli.py
spyctl/filter_resource.py
spyctl/schemas_v2.py
spyctl/spyctl.py
spyctl/spyctl_lib.py
spyctl/api/__init__.py
spyctl/api/agent_health.py
spyctl/api/agents.py
spyctl/api/api_testing.py
spyctl/api/athena_search.py
spyctl/api/clusters.py
spyctl/api/custom_flags.py
spyctl/api/logs.py
spyctl/api/notification_targets.py
spyctl/api/notification_templates.py
spyctl/api/notifications.py
spyctl/api/objects.py
spyctl/api/orgs.py
spyctl/api/policies.py
spyctl/api/primitives.py
spyctl/api/pypi.py
spyctl/api/reports.py
spyctl/api/rulesets.py
spyctl/api/saved_queries.py
spyctl/api/search_sets.py
spyctl/api/sources.py
spyctl/archive/old_args.py
spyctl/archive/old_merge.py
spyctl/commands/__init__.py
spyctl/commands/config.py
spyctl/commands/describe.py
spyctl/commands/diff.py
spyctl/commands/edit.py
spyctl/commands/export.py
spyctl/commands/get_object.py
spyctl/commands/logs.py
spyctl/commands/merge.py
spyctl/commands/print_file.py
spyctl/commands/report.py
spyctl/commands/search.py
spyctl/commands/show_schema.py
spyctl/commands/spy_import.py
spyctl/commands/suppress.py
spyctl/commands/test_notification.py
spyctl/commands/update.py
spyctl/commands/validate.py
spyctl/commands/apply_cmd/__init__.py
spyctl/commands/apply_cmd/agent_health.py
spyctl/commands/apply_cmd/apply.py
spyctl/commands/apply_cmd/notification_target.py
spyctl/commands/apply_cmd/notification_template.py
spyctl/commands/create/__init__.py
spyctl/commands/create/agent_health.py
spyctl/commands/create/cluster_policy.py
spyctl/commands/create/container_policy.py
spyctl/commands/create/container_ruleset.py
spyctl/commands/create/create_cmd_group.py
spyctl/commands/create/custom_flag.py
spyctl/commands/create/linux_svc_policy.py
spyctl/commands/create/notification_target.py
spyctl/commands/create/notification_template.py
spyctl/commands/create/saved_query.py
spyctl/commands/create/search_set.py
spyctl/commands/create/trace_suppression_policy.py
spyctl-0.24.1.dist-info/licenses/LICENSE
spyctl-0.24.1.dist-info/METADATA
spyctl-0.24.1.dist-info/WHEEL
spyctl-0.24.1.dist-info/entry_points.txt
spyctl-0.24.1.dist-info/top_level.txt
spyctl-0.24.1.dist-info/RECORD
