Metadata-Version: 2.4
Name: spyctl
Version: 0.24.1
Summary: A command line tool for viewing and managing Spyderbat Resources
Author-email: Brent Haub <dev@spyderbat.com>, Kyle Smith Hanna <dev@spyderbat.com>, Guy Duchatelet <dev@spyderbat.com>, Ruhika Bulani <dev@spyderbat.com>
Maintainer-email: Brent Haub <dev@spyderbat.com>
Project-URL: Homepage, https://spyctl.readthedocs.io/en/latest/
Project-URL: Documentation, https://spyctl.readthedocs.io/en/latest/
Project-URL: Source, https://github.com/spyderbat/spyctl
Project-URL: Spyderbat, https://www.spyderbat.com/
Keywords: spyctl,spyderbat,kubectl,kubernetes
Classifier: Development Status :: 3 - Alpha
Classifier: Programming Language :: Python :: 3
Classifier: Operating System :: OS Independent
Requires-Python: >=3.10
License-File: LICENSE
Requires-Dist: click>=8.1.8
Requires-Dist: click-aliases>=1.0.5
Requires-Dist: pydantic>=2.11.4
Requires-Dist: python-dateutil>=2.9.0.post0
Requires-Dist: pyyaml>=6.0.2
Requires-Dist: requests>=2.32.3
Requires-Dist: tabulate>=0.9.0
Requires-Dist: tqdm>=4.67.1
Requires-Dist: typing-extensions>=4.13.2
Requires-Dist: zulu>=2.0.1
Dynamic: license-file
